prp/__init__.py
prp/__main__.py
prp/appdirs.py
prp/cli.py
prp/config.py
prp/utils.py
prp-0.3.0.dist-info/entry_points.txt
prp-0.3.0.dist-info/LICENSE
prp-0.3.0.dist-info/WHEEL
prp-0.3.0.dist-info/METADATA
prp-0.3.0.dist-info/RECORD
