Metadata-Version: 2.1
Name: prp
Version: 0.3.0
Summary: PRP - a Python runner
Home-page: https://github.com/brettatoms/prp
License: UNKNOWN
Author: Brett Adams
Author-email: brettadams@fastmail.com
Requires-Python: >=3.5,<=4.0a0
Classifier: Intended Audience :: Developers
Classifier: License :: OSI Approved :: MIT License
Classifier: Programming Language :: Python :: 3
Classifier: Topic :: Software Development :: Libraries :: Python Modules
Requires-Dist: toml == 0.10.0
